ttldict/__init__.py
ttldict/ttldict.py
pyttldict-1.0.0.dist-info/LICENSE
pyttldict-1.0.0.dist-info/METADATA
pyttldict-1.0.0.dist-info/WHEEL
pyttldict-1.0.0.dist-info/top_level.txt
pyttldict-1.0.0.dist-info/RECORD
