Metadata-Version: 2.1
Name: pyttldict
Version: 1.0.0
Summary: Python Dictionary with timed expiring keys
Author-email: Gurjant Kalsi <me@gurjantkalsi.com>
License: MIT License
Project-URL: Homepage, https://github.com/gkalsi/ttl-dict
Keywords: ttl,expiry,dictionary,expiring
Classifier: License :: OSI Approved :: MIT License
Classifier: Programming Language :: Python
Classifier: Programming Language :: Python :: 3
Requires-Python: >=3.9
License-File: LICENSE
